CHANGELOG.txt
LICENSE.txt
MANIFEST.in
README.md
setup.py
Km2/__init__.py
coba_aansyawaluddinn.egg-info/PKG-INFO
coba_aansyawaluddinn.egg-info/SOURCES.txt
coba_aansyawaluddinn.egg-info/dependency_links.txt
coba_aansyawaluddinn.egg-info/top_level.txt